iffiisol/__init__.py
iffiisol/fn.py
iffiisol-0.0.1.dist-info/LICENSE.txt
iffiisol-0.0.1.dist-info/METADATA
iffiisol-0.0.1.dist-info/WHEEL
iffiisol-0.0.1.dist-info/top_level.txt
iffiisol-0.0.1.dist-info/RECORD
