Metadata-Version: 2.1
Name: iffiisol
Version: 0.0.1
Summary: iffiisol
Author: Iffiisyed
Author-email: iffiisyed@gmail.com
Keywords: arithmetic,math,mathematics,python tutorial,iffiisyed
Classifier: Development Status :: 1 - Planning
Classifier: Intended Audience :: Developers
Classifier: Programming Language :: Python :: 3
Classifier: Operating System :: Unix
Classifier: Operating System :: MacOS :: MacOS X
Classifier: Operating System :: Microsoft :: Windows
License-File: LICENSE.txt
